fmplib/__init__.py
fmplib/const.py
fmplib/fmputils.py
fmplib/main.py
fmplib/search.py
fmplib-0.0.4.dist-info/METADATA
fmplib-0.0.4.dist-info/WHEEL
fmplib-0.0.4.dist-info/top_level.txt
fmplib-0.0.4.dist-info/RECORD
