Metadata-Version: 2.4
Name: fmplib
Version: 0.0.4
Summary: Library to access Financial Modeling Prep API
Author: AlgoÉTS
Requires-Dist: python-dotenv
Requires-Dist: requests
Dynamic: author
Dynamic: requires-dist
Dynamic: summary
